xiaoTangPypi/__init__.py
xiaoTangPypi/xiaoTangTest.py
xiaoTangPypi-0.0.1.dist-info/METADATA
xiaoTangPypi-0.0.1.dist-info/WHEEL
xiaoTangPypi-0.0.1.dist-info/top_level.txt
xiaoTangPypi-0.0.1.dist-info/RECORD
